libcasm/clusterography/__init__.py
libcasm/clusterography/_clusterography.cpython-313-darwin.so
libcasm/clusterography/_methods.py
libcasm/configuration/__init__.py
libcasm/configuration/_configuration.cpython-313-darwin.so
libcasm/configuration/_methods.py
libcasm/configuration/_misc.py
libcasm/configuration/io/__init__.py
libcasm/configuration/io/_symgroup.py
libcasm/configuration/io/spglib.py
libcasm/configuration/io/tools.py
libcasm/enumerate/_ConfigEnumAllOccupations.py
libcasm/enumerate/_ConfigEnumInfo.py
libcasm/enumerate/_ConfigEnumLocalOccupations.py
libcasm/enumerate/_ConfigEnumMeshGrid.py
libcasm/enumerate/_ScelEnum.py
libcasm/enumerate/_SuperConfigEnum.py
libcasm/enumerate/_SuperlatticeEnum.py
libcasm/enumerate/__init__.py
libcasm/enumerate/_enumerate.cpython-313-darwin.so
libcasm/enumerate/_make_distinct_super_configurations.py
libcasm/enumerate/_methods.py
libcasm/enumerate/_point_defect_supercell_methods.py
libcasm/include/casm/configuration/ConfigCompare.hh
libcasm/include/casm/configuration/ConfigDoFIsEquivalent.hh
libcasm/include/casm/configuration/ConfigIsEquivalent.hh
libcasm/include/casm/configuration/Configuration.hh
libcasm/include/casm/configuration/ConfigurationSet.hh
libcasm/include/casm/configuration/DoFSpace_functions.hh
libcasm/include/casm/configuration/FromStructure.hh
libcasm/include/casm/configuration/Prim.hh
libcasm/include/casm/configuration/PrimMagspinInfo.hh
libcasm/include/casm/configuration/PrimSymInfo.hh
libcasm/include/casm/configuration/Supercell.hh
libcasm/include/casm/configuration/SupercellSet.hh
libcasm/include/casm/configuration/SupercellSymInfo.hh
libcasm/include/casm/configuration/SupercellSymOp.hh
libcasm/include/casm/configuration/canonical_form.hh
libcasm/include/casm/configuration/config_space_analysis.hh
libcasm/include/casm/configuration/copy_configuration.hh
libcasm/include/casm/configuration/definitions.hh
libcasm/include/casm/configuration/dof_space_analysis.hh
libcasm_configuration-2.2.0.dist-info/licenses/LICENSE
libcasm_configuration-2.2.0.dist-info/METADATA
libcasm_configuration-2.2.0.dist-info/WHEEL
libcasm_configuration-2.2.0.dist-info/top_level.txt
libcasm_configuration-2.2.0.dist-info/RECORD
